{
  "lastUpdated": "2025-12-02T00:00:00Z",
  "categories": {
    "Academic": {
      "displayName": "Academic Certificates",
      "icon": "fa-graduation-cap",
      "description": "Educational certificates and marksheets",
      "certificates": [
        {
          "id": "hsc-certificate",
          "title": "HSC Certificate",
          "category": "Academic",
          "subcategory": "HSC",
          "issuedBy": "Dinajpur Education Board",
          "issuedDate": "2023",
          "fileType": "pdf",
          "fileName": "HSC Certificate.pdf",
          "filePath": "CERTIFICATES/Academic/HSC/HSC Certificate.pdf",
          "thumbnail": "CERTIFICATES/Academic/HSC/HSC Certificate.jpg",
          "description": "Higher Secondary Certificate - Science, GPA 5.00",
          "tags": ["education", "hsc", "science"],
          "verified": true,
          "featured": true
        }
      ]
    },
    "Medical": {
      "displayName": "Medical Certificates",
      "icon": "fa-heart-pulse",
      "description": "Health and medical documents",
      "certificates": [
        {
          "id": "covid-vaccine",
          "title": "COVID-19 Vaccination Certificate",
          "category": "Medical",
          "subcategory": "Vaccination",
          "issuedBy": "Government of Bangladesh",
          "issuedDate": "2021",
          "fileType": "pdf",
          "fileName": "Corona Vaccination Certificate.pdf",
          "filePath": "CERTIFICATES/Medical/Corona Vaccination Certificate.pdf",
          "thumbnail": "CERTIFICATES/Medical/Corona Vaccination Certificate.jpg",
          "description": "Complete COVID-19 vaccination certification",
          "tags": ["health", "vaccination", "covid-19"],
          "verified": true,
          "featured": false
        },
        {
          "id": "blood-group",
          "title": "Blood Group Report",
          "category": "Medical",
          "subcategory": "Reports",
          "issuedBy": "Medical Center",
          "issuedDate": "2024",
          "fileType": "jpg",
          "fileName": "Blood Group Report.jpg",
          "filePath": "CERTIFICATES/Medical/Blood Group Report.jpg",
          "thumbnail": "CERTIFICATES/Medical/Blood Group Report.jpg",
          "description": "Blood group test report and medical information",
          "tags": ["health", "blood-group", "medical-report"],
          "verified": true,
          "featured": false
        },
        {
          "id": "nationality-certificate",
          "title": "Nationality & Character Certificate",
          "category": "Medical",
          "subcategory": "Legal",
          "issuedBy": "Government Authority",
          "issuedDate": "2024",
          "fileType": "jpg",
          "fileName": "Nationality & Character Certificate.jpg",
          "filePath": "CERTIFICATES/Medical/Nationality & Character Certificate.jpg",
          "thumbnail": "CERTIFICATES/Medical/Nationality & Character Certificate.jpg",
          "description": "Official nationality and character verification certificate",
          "tags": ["legal", "nationality", "character"],
          "verified": true,
          "featured": false
        }
      ]
    },
    "Skill": {
      "displayName": "Skill Certificates",
      "icon": "fa-award",
      "description": "Professional skills and training certificates",
      "certificates": [
        {
          "id": "git-freshers",
          "title": "Git For Freshers",
          "category": "Skill",
          "subcategory": "Programming",
          "issuedBy": "Training Provider",
          "issuedDate": "2024",
          "fileType": "pdf",
          "fileName": "Git Certificate.pdf",
          "filePath": "CERTIFICATES/Skill/Git For Freshers/Git Certificate.pdf",
          "thumbnail": "CERTIFICATES/Skill/Git For Freshers/thumbnail.jpg",
          "description": "Git version control training certification",
          "tags": ["programming", "git", "version-control"],
          "verified": true,
          "featured": true
        },
        {
          "id": "ms365-copilot",
          "title": "Microsoft 365 Copilot",
          "category": "Skill",
          "subcategory": "AI Tools",
          "issuedBy": "Microsoft",
          "issuedDate": "2024",
          "fileType": "pdf",
          "fileName": "MS365 Copilot Certificate.pdf",
          "filePath": "CERTIFICATES/Skill/Microsoft 365 Copilot/MS365 Copilot Certificate.pdf",
          "thumbnail": "CERTIFICATES/Skill/Microsoft 365 Copilot/thumbnail.jpg",
          "description": "Microsoft 365 Copilot AI productivity training",
          "tags": ["ai", "microsoft", "productivity"],
          "verified": true,
          "featured": true
        }
      ]
    }
  },
  "stats": {
    "totalCertificates": 7,
    "academicCount": 1,
    "medicalCount": 3,
    "skillCount": 2
  }
}
